intabular/__init__.py
intabular/__main__.py
intabular/cli.py
intabular/csv_component.py
intabular/main.py
intabular/core/__init__.py
intabular/core/analyzer.py
intabular/core/config.py
intabular/core/llm_logger.py
intabular/core/logging_config.py
intabular/core/processor.py
intabular/core/strategy.py
intabular/core/utils.py
intabular-0.1.1.dist-info/licenses/LICENSE
intabular-0.1.1.dist-info/METADATA
intabular-0.1.1.dist-info/WHEEL
intabular-0.1.1.dist-info/entry_points.txt
intabular-0.1.1.dist-info/top_level.txt
intabular-0.1.1.dist-info/RECORD
