Metadata-Version: 2.4
Name: intabular
Version: 0.1.1
Summary: Intelligent Table Data Ingestion - AI-powered CSV mapping and schema alignment
Author-email: Alexander Krauck <alexander.krauck@gmail.com>
Maintainer-email: Alexander Krauck <alexander.krauck@gmail.com>
License-Expression: MIT
Project-URL: Homepage, https://github.com/alexanderkrauck/intabular
Project-URL: Documentation, https://github.com/alexanderkrauck/intabular#readme
Project-URL: Repository, https://github.com/alexanderkrauck/intabular.git
Project-URL: Bug Tracker, https://github.com/alexanderkrauck/intabular/issues
Keywords: csv,data-ingestion,ai,llm,data-mapping,schema-alignment,pandas
Classifier: Development Status :: 4 - Beta
Classifier: Intended Audience :: Developers
Classifier: Intended Audience :: Science/Research
Classifier: Operating System :: OS Independent
Classifier: Programming Language :: Python :: 3
Classifier: Programming Language :: Python :: 3.8
Classifier: Programming Language :: Python :: 3.9
Classifier: Programming Language :: Python :: 3.10
Classifier: Programming Language :: Python :: 3.11
Classifier: Programming Language :: Python :: 3.12
Classifier: Topic :: Scientific/Engineering :: Artificial Intelligence
Classifier: Topic :: Scientific/Engineering :: Information Analysis
Classifier: Topic :: Office/Business :: Financial :: Spreadsheet
Classifier: Topic :: Software Development :: Libraries :: Python Modules
Requires-Python: >=3.8
License-File: LICENSE
Requires-Dist: openai>=1.0.0
Requires-Dist: pandas>=2.0.0
Requires-Dist: numpy>=1.20.0
Requires-Dist: python-dotenv>=1.0.0
Requires-Dist: PyYAML>=6.0.0
Provides-Extra: dev
Requires-Dist: pytest>=7.0; extra == "dev"
Requires-Dist: black>=22.0; extra == "dev"
Requires-Dist: flake8>=4.0; extra == "dev"
Requires-Dist: mypy>=0.910; extra == "dev"
Dynamic: license-file
